pyreiseamt/__init__.py
pyreiseamt/__main__.py
pyreiseamt/scorer.py
pyreiseamt/scraper.py
pyreiseamt/sentiment_dict.obj
pyreiseamt/stopwords.obj
pyreiseamt-0.0.1.dist-info/LICENSE
pyreiseamt-0.0.1.dist-info/METADATA
pyreiseamt-0.0.1.dist-info/WHEEL
pyreiseamt-0.0.1.dist-info/entry_points.txt
pyreiseamt-0.0.1.dist-info/top_level.txt
pyreiseamt-0.0.1.dist-info/RECORD
