Metadata-Version: 2.1
Name: pyreiseamt
Version: 0.0.1
Summary: Package to crawl country information of German Foreign Office
Home-page: https://github.com/Jhruzik/pyreiseamt
Author: Joshua Hruzik
Author-email: joshua.hruzik@gmail.com
License: UNKNOWN
Platform: UNKNOWN
Classifier: Programming Language :: Python :: 3
Classifier: License :: OSI Approved :: MIT License
Classifier: Operating System :: OS Independent
Classifier: Development Status :: 3 - Alpha
Classifier: Environment :: Console
Classifier: Intended Audience :: Science/Research
Classifier: Topic :: Internet :: WWW/HTTP
Requires-Dist: requests
Requires-Dist: bs4
Requires-Dist: lxml
